memory_foam/__init__.py
memory_foam/asyn.py
memory_foam/dttime.py
memory_foam/file.py
memory_foam/glob.py
memory_foam/client/__init__.py
memory_foam/client/azure.py
memory_foam/client/fsspec.py
memory_foam/client/gcs.py
memory_foam/client/s3.py
memory_foam-0.3.2.dist-info/licenses/LICENSE
memory_foam-0.3.2.dist-info/METADATA
memory_foam-0.3.2.dist-info/WHEEL
memory_foam-0.3.2.dist-info/top_level.txt
memory_foam-0.3.2.dist-info/RECORD
