Metadata-Version: 2.4
Name: memory-foam
Version: 0.3.2
Summary: Performant iterators for loading files from S3, GCS and Azure into memory for easy processing.
Author-email: Matt Seddon <mattseddon@hotmail.com>
License: Apache-2.0
Project-URL: Documentation, https://github.com/mattseddon/memory-foam
Project-URL: Issues, https://github.com/mattseddon/memory-foam/issues
Project-URL: Source, https://github.com/mattseddon/memory-foam
Classifier: Programming Language :: Python :: 3
Classifier: Programming Language :: Python :: 3.9
Classifier: Programming Language :: Python :: 3.10
Classifier: Programming Language :: Python :: 3.11
Classifier: Programming Language :: Python :: 3.12
Classifier: Programming Language :: Python :: 3.13
Classifier: Development Status :: 2 - Pre-Alpha
Requires-Python: >=3.9
License-File: LICENSE
Requires-Dist: fsspec>=2024.2.0
Requires-Dist: adlfs>=2024.2.0
Requires-Dist: gcsfs>=2024.2.0
Requires-Dist: s3fs>=2024.2.0
Requires-Dist: python-dateutil>=2
Provides-Extra: tests
Requires-Dist: pytest<9,>=8; extra == "tests"
Requires-Dist: pytest-sugar>=0.9.6; extra == "tests"
Requires-Dist: pytest-cov>=4.1.0; extra == "tests"
Requires-Dist: pytest-mock>=3.12.0; extra == "tests"
Requires-Dist: pytest-servers[all]>=0.5.9; extra == "tests"
Requires-Dist: hypothesis; extra == "tests"
Provides-Extra: dev
Requires-Dist: memory_foam[tests]; extra == "dev"
Requires-Dist: mypy==1.15.0; extra == "dev"
Requires-Dist: types-python-dateutil; extra == "dev"
Provides-Extra: examples
Requires-Dist: dlt[duckdb]; extra == "examples"
Requires-Dist: huggingface_hub[hf_transfer]; extra == "examples"
Requires-Dist: matplotlib; extra == "examples"
Requires-Dist: open_clip_torch; extra == "examples"
Requires-Dist: pillow; extra == "examples"
Requires-Dist: tqdm; extra == "examples"
Requires-Dist: ultralytics; extra == "examples"
Dynamic: license-file
